LICENSE
README.md
setup.py
damescraping/runtests.sh
damescraping.egg-info/PKG-INFO
damescraping.egg-info/SOURCES.txt
damescraping.egg-info/dependency_links.txt
damescraping.egg-info/not-zip-safe
damescraping.egg-info/requires.txt
damescraping.egg-info/top_level.txt
damescraping/tests/test_mechanicalsoup.py
damescraping/tests/test_newspaper.py
damescraping/tests/test_requests.py