Metadata-Version: 2.1
Name: damescraping
Version: 0.1.1.post1
Summary: Learning Scraping from Tests by David Arroyo Menéndez
Home-page: http://github.com/davidam/damescraping
Author: David Arroyo Menéndez
Author-email: davidam@gnu.org
License: GPLv3
Keywords: scraping tests
Classifier: Development Status :: 3 - Alpha
Classifier: License :: OSI Approved :: GNU General Public License v3 (GPLv3)
Classifier: Programming Language :: Python :: 3.6
Classifier: Topic :: Scientific/Engineering
License-File: LICENSE
